{
  "global": {
    "logAnalyticsWorkspace": {
      "Development": {
        "name": "%ORGANIZATION%-monitoring-dev-ws",
        "resourceGroupName": "%ORGANIZATION%-monitoring-dev-rg"
      },
      "Staging": {
        "name": "%ORGANIZATION%-monitoring-dev-ws",
        "resourceGroupName": "%ORGANIZATION%-monitoring-dev-rg"
      },
      "Production": {
        "name": "%ORGANIZATION%-monitoring-prd-ws",
        "resourceGroupName": "%ORGANIZATION%-monitoring-prd-rg"
      },
      "Shared": {
        "name": "%ORGANIZATION%-monitoring-prd-ws",
        "resourceGroupName": "%ORGANIZATION%-monitoring-prd-rg"
      }
    },
    "apiManagement": {
      "Development": {
        "name": "%ORGANIZATION%-gateway-dev-apim",
        "keyVaultName": "%ORGANIZATION%-gateway-dev-kv",
        "resourceGroupName": "%ORGANIZATION%-gateway-dev-rg"
      },
      "Staging": {
        "name": "%ORGANIZATION%-gateway-dev-apim",
        "keyVaultName": "%ORGANIZATION%-gateway-dev-kv",
        "resourceGroupName": "%ORGANIZATION%-gateway-dev-rg"
      },
      "Production": {
        "name": "%ORGANIZATION%-gateway-prd-apim",
        "keyVaultName": "%ORGANIZATION%-gateway-prd-kv",
        "resourceGroupName": "%ORGANIZATION%-gateway-prd-rg"
      },
      "Shared": {
        "name": "%ORGANIZATION%-gateway-prd-apim",
        "keyVaultName": "%ORGANIZATION%-gateway-prd-kv",
        "resourceGroupName": "%ORGANIZATION%-gateway-prd-rg"
      }
    },
    "dnsZone": {
      "milochau.com": "mil-rg-milochau"
    }
  },
  "naming": {
    "prefix": "%ORGANIZATION%-%APPLICATION%-%HOST%-",
    "suffixes": {
      "appConfiguration": "cfg",
      "logAnalyticsWorkspace": "ws",
      "apiManagement": "apim",
      "apiManagementApi": "apimapi",
      "apiManagementApiVersionSet": "apimversionset",
      "functionsApplication": "fn",
      "applicationInsights": "ai",
      "userAssignedIdentity": "uai",
      "userAssignedIdentityClients": "uaiclients",
      "cdnProfile": "cdnp",
      "cdnEndpoint": "cdne",
      "cosmosAccount": "cosmos",
      "cosmosDatabase": "cosmosdb",
      "servicePlan": "asp",
      "serviceBusNamespace": "sbn",
      "storageAccount": "sto",
      "keyVault": "kv",
      "dashboard": "dsh",
      "staticWebApplication": "swa",
      "webTest": "test"
    }
  }
}